pythontranslate/__init__.py
pythontranslate-0.0.2.dist-info/METADATA
pythontranslate-0.0.2.dist-info/RECORD
pythontranslate-0.0.2.dist-info/WHEEL
pythontranslate-0.0.2.dist-info/top_level.txt
