Metadata-Version: 2.1
Name: pythontranslate
Version: 0.0.2
Summary: Translate your stuff free and online with translate.yandex.com
Home-page: https://github.com/Divirad/PythonTranslate
Author: divirad
Author-email: divirad@gmx.de
License: MIT
Platform: UNKNOWN
